odoo/addons/l10n_es_ticketbai_api_batuz/README.rst
odoo/addons/l10n_es_ticketbai_api_batuz/__init__.py
odoo/addons/l10n_es_ticketbai_api_batuz/__manifest__.py
odoo/addons/l10n_es_ticketbai_api_batuz/data/lroe_chapter_data.xml
odoo/addons/l10n_es_ticketbai_api_batuz/data/tax_agency_data.xml
odoo/addons/l10n_es_ticketbai_api_batuz/i18n/es.po
odoo/addons/l10n_es_ticketbai_api_batuz/i18n/eu.po
odoo/addons/l10n_es_ticketbai_api_batuz/i18n/l10n_es_ticketbai_api_batuz.pot
odoo/addons/l10n_es_ticketbai_api_batuz/lroe/__init__.py
odoo/addons/l10n_es_ticketbai_api_batuz/lroe/lroe_api.py
odoo/addons/l10n_es_ticketbai_api_batuz/lroe/lroe_xml_schema.py
odoo/addons/l10n_es_ticketbai_api_batuz/models/__init__.py
odoo/addons/l10n_es_ticketbai_api_batuz/models/lroe_operation.py
odoo/addons/l10n_es_ticketbai_api_batuz/models/lroe_operation_response.py
odoo/addons/l10n_es_ticketbai_api_batuz/models/res_company.py
odoo/addons/l10n_es_ticketbai_api_batuz/models/ticketbai_invoice.py
odoo/addons/l10n_es_ticketbai_api_batuz/readme/CONTRIBUTORS.rst
odoo/addons/l10n_es_ticketbai_api_batuz/readme/DESCRIPTION.rst
odoo/addons/l10n_es_ticketbai_api_batuz/readme/INSTALL.rst
odoo/addons/l10n_es_ticketbai_api_batuz/security/ir.model.access.csv
odoo/addons/l10n_es_ticketbai_api_batuz/static/description/icon.png
odoo/addons/l10n_es_ticketbai_api_batuz/static/description/index.html
odoo/addons/l10n_es_ticketbai_api_batuz/static/src/description/icon.png
odoo/addons/l10n_es_ticketbai_api_batuz/static/src/img/binovo_logo.jpg
odoo/addons/l10n_es_ticketbai_api_batuz/static/src/img/binovo_logo_peque.jpg
odoo/addons/l10n_es_ticketbai_api_batuz/tests/__init__.py
odoo/addons/l10n_es_ticketbai_api_batuz/tests/company-bizkaia-pf-140.json
odoo/addons/l10n_es_ticketbai_api_batuz/tests/company-bizkaia-pj-240.json
odoo/addons/l10n_es_ticketbai_api_batuz/tests/tbai-batuz-soft-developer.json
odoo/addons/l10n_es_ticketbai_api_batuz/tests/tbai-p12-bizkaia-pf-140.json
odoo12_addon_l10n_es_ticketbai_api_batuz-12.0.1.1.3.dist-info/METADATA
odoo12_addon_l10n_es_ticketbai_api_batuz-12.0.1.1.3.dist-info/WHEEL
odoo12_addon_l10n_es_ticketbai_api_batuz-12.0.1.1.3.dist-info/top_level.txt
odoo12_addon_l10n_es_ticketbai_api_batuz-12.0.1.1.3.dist-info/RECORD
