Metadata-Version: 2.1
Name: odoo12-addon-l10n-es-ticketbai-api-batuz
Version: 12.0.1.1.3
Summary: TicketBAI (API) - Batuz - declaración de todas las operaciones de venta realizadas por las personas y entidades que desarrollan actividades económicas en Bizkaia
Home-page: https://github.com/OCA/l10n-spain
Author: Binovo,Odoo Community Association (OCA)
Author-email: support@odoo-community.org
License: AGPL-3
Platform: UNKNOWN
Classifier: Programming Language :: Python
Classifier: Framework :: Odoo
Classifier: Framework :: Odoo :: 12.0
Classifier: License :: OSI Approved :: GNU Affero General Public License v3
Classifier: Development Status :: 3 - Alpha
Requires-Python: >=3.5
Requires-Dist: odoo12-addon-l10n-es-ticketbai-api
Requires-Dist: odoo (<12.1dev,>=12.0a)
Requires-Dist: requests-pkcs12
Requires-Dist: xmltodict
